.gitignore
.travis.yml
AUTHORS
CHANGES.md
LICENSE
README.rst
example.py
setup.cfg
setup.py
tests.py
virtualenvapi/__init__.py
virtualenvapi/exceptions.py
virtualenvapi/manage.py
virtualenvapi/util.py
zerotk.virtualenv_api.egg-info/PKG-INFO
zerotk.virtualenv_api.egg-info/SOURCES.txt
zerotk.virtualenv_api.egg-info/dependency_links.txt
zerotk.virtualenv_api.egg-info/requires.txt
zerotk.virtualenv_api.egg-info/top_level.txt