Metadata-Version: 1.1
Name: zerotk.virtualenv-api
Version: 2.2.0
Summary: An API for virtualenv/pip
Home-page: https://github.com/zerotk/virtualenv-api
Author: Sam Kingston and AUTHORS
Author-email: sam@sjkwi.com.au
License: BSD
Platform: UNKNOWN
Classifier: Development Status :: 5 - Production/Stable
Classifier: Intended Audience :: Developers
Classifier: License :: OSI Approved :: BSD License
Classifier: Operating System :: OS Independent
Classifier: Programming Language :: Python
Classifier: Programming Language :: Python :: 2
Classifier: Programming Language :: Python :: 2.7
Classifier: Programming Language :: Python :: 3.3
Classifier: Programming Language :: Python :: 3.4
Classifier: Programming Language :: Python :: 3.5
Classifier: Topic :: Software Development :: Libraries :: Python Modules
